pyipf/__init__.py
pyipf/pyipf.py
pyipf-0.1.0.dist-info/METADATA
pyipf-0.1.0.dist-info/WHEEL
pyipf-0.1.0.dist-info/licenses/LICENSE
pyipf-0.1.0.dist-info/RECORD
