Metadata-Version: 2.1
Name: pyipf
Version: 0.1.0
Summary: Iterative Proportional Weighting in Python
Project-URL: Homepage, https://github.com/FuzzyDuck79/pyipf
Author-email: Mutahar Chalmers <mutahar.chalmers@gmail.com>
License: MIT License
License-File: LICENSE
Classifier: Development Status :: 4 - Beta
Classifier: Intended Audience :: Science/Research
Classifier: License :: OSI Approved :: MIT License
Classifier: Operating System :: OS Independent
Classifier: Programming Language :: Python :: 3
Classifier: Topic :: Scientific/Engineering
Requires-Python: >=3.8
Requires-Dist: numpy>=1.18
Requires-Dist: tqdm>=4.63
